fairseq2/__init__.py
fairseq2/cluster.py
fairseq2/data_type.py
fairseq2/device.py
fairseq2/early_stopper.py
fairseq2/error.py
fairseq2/file_system.py
fairseq2/gang.py
fairseq2/io.py
fairseq2/logging.py
fairseq2/py.typed
fairseq2/sharder.py
fairseq2/typing.py
fairseq2/world_info.py
fairseq2/assets/__init__.py
fairseq2/assets/__main__.py
fairseq2/assets/card.py
fairseq2/assets/cli.py
fairseq2/assets/dirs.py
fairseq2/assets/download_manager.py
fairseq2/assets/metadata_provider.py
fairseq2/assets/store.py
fairseq2/assets/cards/datasets/librilight.yaml
fairseq2/assets/cards/datasets/librispeech.yaml
fairseq2/assets/cards/datasets/openeft.yaml
fairseq2/assets/cards/models/jepa.yaml
fairseq2/assets/cards/models/llama.yaml
fairseq2/assets/cards/models/mistral.yaml
fairseq2/assets/cards/models/nllb.yaml
fairseq2/assets/cards/models/qwen.yaml
fairseq2/assets/cards/models/s2t_conformer.yaml
fairseq2/assets/cards/models/s2t_transformer.yaml
fairseq2/assets/cards/models/wav2vec2.yaml
fairseq2/checkpoint/__init__.py
fairseq2/checkpoint/hg.py
fairseq2/checkpoint/manager.py
fairseq2/checkpoint/model_metadata.py
fairseq2/composition/__init__.py
fairseq2/composition/assets.py
fairseq2/composition/datasets.py
fairseq2/composition/extensions.py
fairseq2/composition/lib.py
fairseq2/composition/models.py
fairseq2/composition/tokenizers.py
fairseq2/data/__init__.py
fairseq2/data/_memory.py
fairseq2/data/audio.py
fairseq2/data/data_pipeline.py
fairseq2/data/image.py
fairseq2/data/utils.py
fairseq2/data/parquet/__init__.py
fairseq2/data/parquet/arrow_transform.py
fairseq2/data/parquet/utils.py
fairseq2/data/parquet/fragment_loading/__init__.py
fairseq2/data/parquet/fragment_loading/builder.py
fairseq2/data/parquet/fragment_loading/config.py
fairseq2/data/parquet/fragment_streaming/__init__.py
fairseq2/data/parquet/fragment_streaming/builder.py
fairseq2/data/parquet/fragment_streaming/config.py
fairseq2/data/parquet/fragment_streaming/primitives.py
fairseq2-0.7.0.dist-info/LICENSE
fairseq2-0.7.0.dist-info/METADATA
fairseq2-0.7.0.dist-info/WHEEL
fairseq2-0.7.0.dist-info/top_level.txt
fairseq2-0.7.0.dist-info/RECORD
