Metadata-Version: 2.2
Name: fairseq2
Version: 0.7.0
Summary: FAIR Sequence Modeling Toolkit
Home-page: https://github.com/facebookresearch/fairseq2
Author: Fundamental AI Research (FAIR) at Meta
License: MIT
Keywords: machine learning
Classifier: Development Status :: 4 - Beta
Classifier: Intended Audience :: Developers
Classifier: Intended Audience :: Science/Research
Classifier: License :: OSI Approved :: MIT License
Classifier: Programming Language :: Python :: 3
Classifier: Programming Language :: Python :: 3.10
Classifier: Programming Language :: Python :: 3.11
Classifier: Programming Language :: Python :: 3.12
Classifier: Topic :: Scientific/Engineering :: Artificial Intelligence
Requires-Python: >=3.10
License-File: LICENSE
Requires-Dist: clusterscope~=0.0.31
Requires-Dist: editdistance~=0.8
Requires-Dist: fairseq2n==0.7.0
Requires-Dist: huggingface_hub~=0.32
Requires-Dist: importlib_metadata~=7.0
Requires-Dist: importlib_resources~=6.4
Requires-Dist: mypy-extensions~=1.0
Requires-Dist: numpy~=1.23
Requires-Dist: packaging~=24.1
Requires-Dist: psutil~=5.9
Requires-Dist: ruamel.yaml~=0.18
Requires-Dist: rich~=13.7
Requires-Dist: sacrebleu~=2.4
Requires-Dist: safetensors~=0.6
Requires-Dist: tiktoken~=0.7
Requires-Dist: torcheval~=0.0.6
Requires-Dist: typing_extensions~=4.12
Requires-Dist: blobfile~=3.0.0
Provides-Extra: arrow
Requires-Dist: pyarrow>=17.0.0; extra == "arrow"
Requires-Dist: retrying~=1.3.4; extra == "arrow"
Requires-Dist: polars>=1.19.0; extra == "arrow"
Requires-Dist: xxhash~=3.5; extra == "arrow"
Dynamic: author
Dynamic: classifier
Dynamic: description
Dynamic: description-content-type
Dynamic: home-page
Dynamic: keywords
Dynamic: license
Dynamic: provides-extra
Dynamic: requires-dist
Dynamic: requires-python
Dynamic: summary
